<annotation>
	<folder>Images</folder>
	<filename>img_137.png</filename>
	<path>C:\Users\podockonnik\Documents\Work\Images\img_137.png</path>
	<source>
		<database>Unknown</database>
	</source>
	<size>
		<width>950</width>
		<height>509</height>
		<depth>3</depth>
	</size>
	<segmented>0</segmented>
	<object>
		<name>cantilever</name>
		<pose>Unspecified</pose>
		<truncated>0</truncated>
		<difficult>0</difficult>
		<bndbox>
			<xmin>286</xmin>
			<ymin>258</ymin>
			<xmax>336</xmax>
			<ymax>324</ymax>
		</bndbox>
	</object>
	<object>
		<name>signboard</name>
		<pose>Unspecified</pose>
		<truncated>0</truncated>
		<difficult>0</difficult>
		<bndbox>
			<xmin>14</xmin>
			<ymin>268</ymin>
			<xmax>152</xmax>
			<ymax>322</ymax>
		</bndbox>
	</object>
	<object>
		<name>signboard</name>
		<pose>Unspecified</pose>
		<truncated>0</truncated>
		<difficult>0</difficult>
		<bndbox>
			<xmin>754</xmin>
			<ymin>282</ymin>
			<xmax>943</xmax>
			<ymax>331</ymax>
		</bndbox>
	</object>
	<object>
		<name>signboard</name>
		<pose>Unspecified</pose>
		<truncated>0</truncated>
		<difficult>0</difficult>
		<bndbox>
			<xmin>341</xmin>
			<ymin>271</ymin>
			<xmax>684</xmax>
			<ymax>328</ymax>
		</bndbox>
	</object>
	<object>
		<name>window</name>
		<pose>Unspecified</pose>
		<truncated>0</truncated>
		<difficult>0</difficult>
		<bndbox>
			<xmin>37</xmin>
			<ymin>68</ymin>
			<xmax>122</xmax>
			<ymax>219</ymax>
		</bndbox>
	</object>
	<object>
		<name>window</name>
		<pose>Unspecified</pose>
		<truncated>0</truncated>
		<difficult>0</difficult>
		<bndbox>
			<xmin>208</xmin>
			<ymin>70</ymin>
			<xmax>295</xmax>
			<ymax>227</ymax>
		</bndbox>
	</object>
	<object>
		<name>window</name>
		<pose>Unspecified</pose>
		<truncated>0</truncated>
		<difficult>0</difficult>
		<bndbox>
			<xmin>395</xmin>
			<ymin>71</ymin>
			<xmax>475</xmax>
			<ymax>227</ymax>
		</bndbox>
	</object>
	<object>
		<name>window</name>
		<pose>Unspecified</pose>
		<truncated>0</truncated>
		<difficult>0</difficult>
		<bndbox>
			<xmin>560</xmin>
			<ymin>82</ymin>
			<xmax>609</xmax>
			<ymax>235</ymax>
		</bndbox>
	</object>
	<object>
		<name>window</name>
		<pose>Unspecified</pose>
		<truncated>0</truncated>
		<difficult>0</difficult>
		<bndbox>
			<xmin>755</xmin>
			<ymin>92</ymin>
			<xmax>829</xmax>
			<ymax>226</ymax>
		</bndbox>
	</object>
	<object>
		<name>door</name>
		<pose>Unspecified</pose>
		<truncated>0</truncated>
		<difficult>0</difficult>
		<bndbox>
			<xmin>762</xmin>
			<ymin>335</ymin>
			<xmax>831</xmax>
			<ymax>468</ymax>
		</bndbox>
	</object>
	<object>
		<name>door</name>
		<pose>Unspecified</pose>
		<truncated>0</truncated>
		<difficult>0</difficult>
		<bndbox>
			<xmin>27</xmin>
			<ymin>330</ymin>
			<xmax>135</xmax>
			<ymax>483</ymax>
		</bndbox>
	</object>
	<object>
		<name>window</name>
		<pose>Unspecified</pose>
		<truncated>0</truncated>
		<difficult>0</difficult>
		<bndbox>
			<xmin>197</xmin>
			<ymin>327</ymin>
			<xmax>295</xmax>
			<ymax>461</ymax>
		</bndbox>
	</object>
	<object>
		<name>window</name>
		<pose>Unspecified</pose>
		<truncated>0</truncated>
		<difficult>0</difficult>
		<bndbox>
			<xmin>400</xmin>
			<ymin>334</ymin>
			<xmax>485</xmax>
			<ymax>457</ymax>
		</bndbox>
	</object>
</annotation>
