<annotation>
	<folder>Images</folder>
	<filename>img_265.png</filename>
	<path>C:\Users\podockonnik\Documents\Work\Images\img_265.png</path>
	<source>
		<database>Unknown</database>
	</source>
	<size>
		<width>859</width>
		<height>871</height>
		<depth>3</depth>
	</size>
	<segmented>0</segmented>
	<object>
		<name>window</name>
		<pose>Unspecified</pose>
		<truncated>0</truncated>
		<difficult>0</difficult>
		<bndbox>
			<xmin>108</xmin>
			<ymin>94</ymin>
			<xmax>194</xmax>
			<ymax>238</ymax>
		</bndbox>
	</object>
	<object>
		<name>window</name>
		<pose>Unspecified</pose>
		<truncated>0</truncated>
		<difficult>0</difficult>
		<bndbox>
			<xmin>342</xmin>
			<ymin>109</ymin>
			<xmax>426</xmax>
			<ymax>245</ymax>
		</bndbox>
	</object>
	<object>
		<name>window</name>
		<pose>Unspecified</pose>
		<truncated>0</truncated>
		<difficult>0</difficult>
		<bndbox>
			<xmin>578</xmin>
			<ymin>116</ymin>
			<xmax>648</xmax>
			<ymax>248</ymax>
		</bndbox>
	</object>
	<object>
		<name>signboard</name>
		<pose>Unspecified</pose>
		<truncated>0</truncated>
		<difficult>0</difficult>
		<bndbox>
			<xmin>384</xmin>
			<ymin>298</ymin>
			<xmax>625</xmax>
			<ymax>373</ymax>
		</bndbox>
	</object>
	<object>
		<name>window</name>
		<pose>Unspecified</pose>
		<truncated>0</truncated>
		<difficult>0</difficult>
		<bndbox>
			<xmin>592</xmin>
			<ymin>415</ymin>
			<xmax>673</xmax>
			<ymax>589</ymax>
		</bndbox>
	</object>
	<object>
		<name>window</name>
		<pose>Unspecified</pose>
		<truncated>0</truncated>
		<difficult>0</difficult>
		<bndbox>
			<xmin>338</xmin>
			<ymin>415</ymin>
			<xmax>423</xmax>
			<ymax>579</ymax>
		</bndbox>
	</object>
	<object>
		<name>window</name>
		<pose>Unspecified</pose>
		<truncated>0</truncated>
		<difficult>0</difficult>
		<bndbox>
			<xmin>70</xmin>
			<ymin>411</ymin>
			<xmax>171</xmax>
			<ymax>576</ymax>
		</bndbox>
	</object>
	<object>
		<name>window</name>
		<pose>Unspecified</pose>
		<truncated>0</truncated>
		<difficult>0</difficult>
		<bndbox>
			<xmin>35</xmin>
			<ymin>753</ymin>
			<xmax>144</xmax>
			<ymax>843</ymax>
		</bndbox>
	</object>
	<object>
		<name>window</name>
		<pose>Unspecified</pose>
		<truncated>0</truncated>
		<difficult>0</difficult>
		<bndbox>
			<xmin>335</xmin>
			<ymin>759</ymin>
			<xmax>431</xmax>
			<ymax>851</ymax>
		</bndbox>
	</object>
	<object>
		<name>window</name>
		<pose>Unspecified</pose>
		<truncated>0</truncated>
		<difficult>0</difficult>
		<bndbox>
			<xmin>617</xmin>
			<ymin>753</ymin>
			<xmax>711</xmax>
			<ymax>851</ymax>
		</bndbox>
	</object>
</annotation>
