<annotation>
	<folder>to jpg</folder>
	<filename>img_470.jpg</filename>
	<path>C:\Users\podockonnik\Desktop\to jpg\img_470.jpg</path>
	<source>
		<database>Unknown</database>
	</source>
	<size>
		<width>1081</width>
		<height>573</height>
		<depth>3</depth>
	</size>
	<segmented>0</segmented>
	<object>
		<name>signboard</name>
		<pose>Unspecified</pose>
		<truncated>0</truncated>
		<difficult>0</difficult>
		<bndbox>
			<xmin>534</xmin>
			<ymin>239</ymin>
			<xmax>730</xmax>
			<ymax>281</ymax>
		</bndbox>
	</object>
	<object>
		<name>signboard</name>
		<pose>Unspecified</pose>
		<truncated>0</truncated>
		<difficult>0</difficult>
		<bndbox>
			<xmin>741</xmin>
			<ymin>309</ymin>
			<xmax>932</xmax>
			<ymax>358</ymax>
		</bndbox>
	</object>
	<object>
		<name>signboard</name>
		<pose>Unspecified</pose>
		<truncated>1</truncated>
		<difficult>0</difficult>
		<bndbox>
			<xmin>890</xmin>
			<ymin>248</ymin>
			<xmax>1081</xmax>
			<ymax>284</ymax>
		</bndbox>
	</object>
	<object>
		<name>signboard</name>
		<pose>Unspecified</pose>
		<truncated>0</truncated>
		<difficult>0</difficult>
		<bndbox>
			<xmin>139</xmin>
			<ymin>266</ymin>
			<xmax>354</xmax>
			<ymax>321</ymax>
		</bndbox>
	</object>
	<object>
		<name>cantilever</name>
		<pose>Unspecified</pose>
		<truncated>0</truncated>
		<difficult>0</difficult>
		<bndbox>
			<xmin>8</xmin>
			<ymin>182</ymin>
			<xmax>100</xmax>
			<ymax>290</ymax>
		</bndbox>
	</object>
	<object>
		<name>door</name>
		<pose>Unspecified</pose>
		<truncated>0</truncated>
		<difficult>0</difficult>
		<bndbox>
			<xmin>810</xmin>
			<ymin>383</ymin>
			<xmax>900</xmax>
			<ymax>560</ymax>
		</bndbox>
	</object>
	<object>
		<name>window</name>
		<pose>Unspecified</pose>
		<truncated>0</truncated>
		<difficult>0</difficult>
		<bndbox>
			<xmin>127</xmin>
			<ymin>51</ymin>
			<xmax>203</xmax>
			<ymax>200</ymax>
		</bndbox>
	</object>
	<object>
		<name>window</name>
		<pose>Unspecified</pose>
		<truncated>0</truncated>
		<difficult>0</difficult>
		<bndbox>
			<xmin>276</xmin>
			<ymin>54</ymin>
			<xmax>353</xmax>
			<ymax>206</ymax>
		</bndbox>
	</object>
	<object>
		<name>window</name>
		<pose>Unspecified</pose>
		<truncated>0</truncated>
		<difficult>0</difficult>
		<bndbox>
			<xmin>424</xmin>
			<ymin>53</ymin>
			<xmax>499</xmax>
			<ymax>199</ymax>
		</bndbox>
	</object>
	<object>
		<name>window</name>
		<pose>Unspecified</pose>
		<truncated>0</truncated>
		<difficult>0</difficult>
		<bndbox>
			<xmin>565</xmin>
			<ymin>50</ymin>
			<xmax>641</xmax>
			<ymax>194</ymax>
		</bndbox>
	</object>
	<object>
		<name>window</name>
		<pose>Unspecified</pose>
		<truncated>0</truncated>
		<difficult>0</difficult>
		<bndbox>
			<xmin>712</xmin>
			<ymin>51</ymin>
			<xmax>780</xmax>
			<ymax>201</ymax>
		</bndbox>
	</object>
	<object>
		<name>window</name>
		<pose>Unspecified</pose>
		<truncated>0</truncated>
		<difficult>0</difficult>
		<bndbox>
			<xmin>853</xmin>
			<ymin>58</ymin>
			<xmax>921</xmax>
			<ymax>200</ymax>
		</bndbox>
	</object>
	<object>
		<name>window</name>
		<pose>Unspecified</pose>
		<truncated>0</truncated>
		<difficult>0</difficult>
		<bndbox>
			<xmin>994</xmin>
			<ymin>56</ymin>
			<xmax>1057</xmax>
			<ymax>203</ymax>
		</bndbox>
	</object>
	<object>
		<name>window</name>
		<pose>Unspecified</pose>
		<truncated>0</truncated>
		<difficult>0</difficult>
		<bndbox>
			<xmin>141</xmin>
			<ymin>325</ymin>
			<xmax>317</xmax>
			<ymax>512</ymax>
		</bndbox>
	</object>
</annotation>
